{
  "diagnostic.displayByAle": true,
  "diagnostic.checkCurrentLine": true,
  "diagnostic.messageTarget": "echo",
  "yaml.completion": true,
  "yaml.format.enable": true,
  "python.linting.flake8Enabled": true,
  "python.linting.flake8Path": "/usr/bin/flake8",
  "yaml.schemas": {
    "https://json.schemastore.org/ansible-playbook": "config.yml"
  },
  "languageserver": {
    "bash": {
      "command": "bash-language-server",
      "args": ["start"],
      "filetypes": ["sh"],
      "ignoredRootPaths": ["~"]
    },
    "ccls": {
      "command": "ccls",
      "filetypes": [
        "c",
        "cpp",
        "objc",
        "objcpp"
      ],
      "rootPatterns": [
        ".ccls",
        "compile_commands.json",
        ".vim/",
        ".git/",
        ".hg/"
      ],
      "initializationOptions": {
        "cache": {
          "directory": "/tmp/ccls"
        }
      }
    }
  }
}
